Workbook

Sheet Read Me
A1: Somos Group budget, calendar 2027
A3: How it works
A4: Fee revenue = billable hours x seasonality weight x billing rate x realization, for each month a person is on staff.
A5: Salaries = annual salary / 12 for each month on staff, with the raise from the raise month. Fringe % is added on top.
A6: Overhead = prior-year actual x (1 + change %), or a fixed amount if you type one, spread evenly over 12 months.
A7: Prior-year revenue and payroll lines marked 'People plan' are replaced by the people plan, so they aren't counted twice.
A8: Drivers = lines you enter: owner draws, guaranteed payments, bonuses, leases, capex. Owner draws sit below net income.
A10: What to edit
A11: Blue text = inputs you can change. Black = formulas. Green = links to another sheet. Yellow = key assumptions.
A12: Assumptions: rates, raises, fringe, realization, seasonality.
A13: People: Include (Y/N), start/end month, salary, billable hours, rate, realization. Add a row for a new hire.
A14: Overhead: Treatment, Change %, or a Fixed amount (overrides Change %).
... A18: Sources: Vantagepoint (employee cost rates, labor detail, targets) and the firm's P&L workbook or GL, as loaded in the dashboard.

Sheet Budget P&L
A1: Budget P&L, calendar 2027
B3: 1 | C3: 2 | D3: 3 | E3: 4 | F3: 5 | G3: 6 | H3: 7 | I3: 8 | J3: 9 | K3: 10 | L3: 11 | M3: 12
A4: Line | B4: Jan | C4: Feb | D4: Mar | E4: Apr | F4: May | G4: Jun | H4: Jul | I4: Aug | J4: Sep | K4: Oct | L4: Nov | M4: Dec | N4: Total | O4: Prior year | P4: Change ($) | Q4: Change %
A5: Revenue
A6: Fee revenue (people plan) | B6: ='Revenue by Person'!C11 -> 231525 | C6: ='Revenue by Person'!D11 -> 220500 | D6: ='Revenue by Person'!E11 -> 253575 | E6: ='Revenue by Person'!F11 -> 242550 | F6: ='Revenue by Person'!G11 -> 231525 | G6: ='Revenue by Person'!H11 -> 242550 | H6: ='Revenue by Person'!I11 -> 242550 | I6: ='Revenue by Person'!J11 -> 242550 | ... M6: ='Revenue by Person'!N11 -> 253575 | N6: =SUM(B6:M6) -> 2877525 | O6: =SUMIFS(Overhead!$F$5:$F$16,Overhead!$A$5:$A$16,"Revenue",Overhead!$E$5:$E$16,"People plan") -> 5024787.2 | P6: =N6-O6 -> -2147262.2 | Q6: =IF(O6=0,"",N6/O6-1) -> -0.42733396
A7: Reimbursed Expenses | B7: =Overhead!$I$7/12 -> 4916.2544 | C7: =Overhead!$I$7/12 -> 4916.2544 | D7: =Overhead!$I$7/12 -> 4916.2544 | E7: =Overhead!$I$7/12 -> 4916.2544 | F7: =Overhead!$I$7/12 -> 4916.2544 | G7: =Overhead!$I$7/12 -> 4916.2544 | H7: =Overhead!$I$7/12 -> 4916.2544 | I7: =Overhead!$I$7/12 -> 4916.2544 | ... M7: =Overhead!$I$7/12 -> 4916.2544 | N7: =SUM(B7:M7) -> 58995.052 | O7: =Overhead!F7 -> 57276.75 | P7: =N7-O7 -> 1718.3025 | Q7: =IF(O7=0,"",N7/O7-1) -> 0.03
A8: Total revenue | B8: =B6+B7 -> 236441.25 | C8: =C6+C7 -> 225416.25 | D8: =D6+D7 -> 258491.25 | E8: =E6+E7 -> 247466.25 | F8: =F6+F7 -> 236441.25 | G8: =G6+G7 -> 247466.25 | H8: =H6+H7 -> 247466.25 | I8: =I6+I7 -> 247466.25 | ... M8: =M6+M7 -> 258491.25 | N8: =SUM(B8:M8) -> 2936520.1 | O8: =SUMIFS(Overhead!$F$5:$F$16,Overhead!$A$5:$A$16,"Revenue",Overhead!$E$5:$E$16,"<>Exclude") -> 5082064 | P8: =N8-O8 -> -2145543.9 | Q8: =IF(O8=0,"",N8/O8-1) -> -0.42217963
A10: Personnel
A11: Salaries (people plan) | B11: ='Salary by Person'!C11 -> 22660 | C11: ='Salary by Person'!D11 -> 22660 | D11: ='Salary by Person'!E11 -> 22660 | E11: ='Salary by Person'!F11 -> 22660 | F11: ='Salary by Person'!G11 -> 22660 | G11: ='Salary by Person'!H11 -> 22660 | H11: ='Salary by Person'!I11 -> 22660 | I11: ='Salary by Person'!J11 -> 22660 | ... M11: ='Salary by Person'!N11 -> 22660 | N11: =SUM(B11:M11) -> 271920
A12: Payroll taxes & benefits (fringe) | B12: =B11*Assumptions!$B$9 -> 3716.24 | C12: =C11*Assumptions!$B$9 -> 3716.24 | D12: =D11*Assumptions!$B$9 -> 3716.24 | E12: =E11*Assumptions!$B$9 -> 3716.24 | F12: =F11*Assumptions!$B$9 -> 3716.24 | G12: =G11*Assumptions!$B$9 -> 3716.24 | H12: =H11*Assumptions!$B$9 -> 3716.24 | I12: =I11*Assumptions!$B$9 -> 3716.24 | ... M12: =M11*Assumptions!$B$9 -> 3716.24 | N12: =SUM(B12:M12) -> 44594.88
A13: Year-end bonus pool | B13: =Drivers!K7 -> 0 | C13: =Drivers!L7 -> 0 | D13: =Drivers!M7 -> 0 | E13: =Drivers!N7 -> 0 | F13: =Drivers!O7 -> 0 | G13: =Drivers!P7 -> 0 | H13: =Drivers!Q7 -> 0 | I13: =Drivers!R7 -> 0 | ... M13: =Drivers!V7 -> 120000 | N13: =SUM(B13:M13) -> 120000
A14: Total personnel | B14: =B11+B12+B13 -> 26376.24 | C14: =C11+C12+C13 -> 26376.24 | D14: =D11+D12+D13 -> 26376.24 | E14: =E11+E12+E13 -> 26376.24 | F14: =F11+F12+F13 -> 26376.24 | G14: =G11+G12+G13 -> 26376.24 | H14: =H11+H12+H13 -> 26376.24 | I14: =I11+I12+I13 -> 26376.24 | ... M14: =M11+M12+M13 -> 146376.24 | N14: =SUM(B14:M14) -> 436514.88 | O14: =SUMIFS(Overhead!$F$5:$F$16,Overhead!$A$5:$A$16,"Expense",Overhead!$E$5:$E$16,"People plan")+SUMIFS(Overhead!$F$5:$F$16,Overhead!$A$5:$A$16,"COGS",Overhead!$E$5:$E$16,"People plan") -> 2092613.7 | P14: =N14-O14 -> -1656098.8 | Q14: =IF(O14=0,"",N14/O14-1) -> -0.79140207
A16: Operating expenses
A17: Rent | B17: =Overhead!$I$12/12 -> 26082.224 | C17: =Overhead!$I$12/12 -> 26082.224 | D17: =Overhead!$I$12/12 -> 26082.224 | E17: =Overhead!$I$12/12 -> 26082.224 | F17: =Overhead!$I$12/12 -> 26082.224 | G17: =Overhead!$I$12/12 -> 26082.224 | H17: =Overhead!$I$12/12 -> 26082.224 | I17: =Overhead!$I$12/12 -> 26082.224 | ... M17: =Overhead!$I$12/12 -> 26082.224 | N17: =SUM(B17:M17) -> 312986.69 | O17: =Overhead!F12 -> 303870.57 | P17: =N17-O17 -> 9116.1171 | Q17: =IF(O17=0,"",N17/O17-1) -> 0.03
A18: Software & Subscriptions | B18: =Overhead!$I$13/12 -> 8447.9355 | C18: =Overhead!$I$13/12 -> 8447.9355 | D18: =Overhead!$I$13/12 -> 8447.9355 | E18: =Overhead!$I$13/12 -> 8447.9355 | F18: =Overhead!$I$13/12 -> 8447.9355 | G18: =Overhead!$I$13/12 -> 8447.9355 | H18: =Overhead!$I$13/12 -> 8447.9355 | I18: =Overhead!$I$13/12 -> 8447.9355 | ... M18: =Overhead!$I$13/12 -> 8447.9355 | N18: =SUM(B18:M18) -> 101375.23 | O18: =Overhead!F13 -> 98422.55 | P18: =N18-O18 -> 2952.6765 | Q18: =IF(O18=0,"",N18/O18-1) -> 0.03
A19: Professional Fees | B19: =Overhead!$I$14/12 -> 4099.6575 | C19: =Overhead!$I$14/12 -> 4099.6575 | D19: =Overhead!$I$14/12 -> 4099.6575 | E19: =Overhead!$I$14/12 -> 4099.6575 | F19: =Overhead!$I$14/12 -> 4099.6575 | G19: =Overhead!$I$14/12 -> 4099.6575 | H19: =Overhead!$I$14/12 -> 4099.6575 | I19: =Overhead!$I$14/12 -> 4099.6575 | ... M19: =Overhead!$I$14/12 -> 4099.6575 | N19: =SUM(B19:M19) -> 49195.89 | O19: =Overhead!F14 -> 47763 | P19: =N19-O19 -> 1432.89 | Q19: =IF(O19=0,"",N19/O19-1) -> 0.03
A20: New office lease | B20: =Drivers!K8 -> 0 | C20: =Drivers!L8 -> 0 | D20: =Drivers!M8 -> 0 | E20: =Drivers!N8 -> 0 | F20: =Drivers!O8 -> 0 | G20: =Drivers!P8 -> 0 | H20: =Drivers!Q8 -> 10000 | I20: =Drivers!R8 -> 10000 | ... M20: =Drivers!V8 -> 10000 | N20: =SUM(B20:M20) -> 60000
A21: Total operating expenses | B21: =B17+B18+B19+B20 -> 38629.817 | C21: =C17+C18+C19+C20 -> 38629.817 | D21: =D17+D18+D19+D20 -> 38629.817 | E21: =E17+E18+E19+E20 -> 38629.817 | F21: =F17+F18+F19+F20 -> 38629.817 | G21: =G17+G18+G19+G20 -> 38629.817 | H21: =H17+H18+H19+H20 -> 48629.817 | I21: =I17+I18+I19+I20 -> 48629.817 | ... M21: =M17+M18+M19+M20 -> 48629.817 | N21: =SUM(B21:M21) -> 523557.8 | O21: =SUMIFS(Overhead!$F$5:$F$16,Overhead!$A$5:$A$16,"Expense",Overhead!$E$5:$E$16,"Prior year + %") -> 450056.12 | P21: =N21-O21 -> 73501.684 | Q21: =IF(O21=0,"",N21/O21-1) -> 0.16331671
A23: Other income & expense
A24: Interest Income | B24: =Overhead!$I$8/12 -> 519.50453 | C24: =Overhead!$I$8/12 -> 519.50453 | D24: =Overhead!$I$8/12 -> 519.50453 | E24: =Overhead!$I$8/12 -> 519.50453 | F24: =Overhead!$I$8/12 -> 519.50453 | G24: =Overhead!$I$8/12 -> 519.50453 | H24: =Overhead!$I$8/12 -> 519.50453 | I24: =Overhead!$I$8/12 -> 519.50453 | ... M24: =Overhead!$I$8/12 -> 519.50453 | N24: =SUM(B24:M24) -> 6234.0544 | O24: =Overhead!F8 -> 6052.48 | P24: =N24-O24 -> 181.5744 | Q24: =IF(O24=0,"",N24/O24-1) -> 0.03
A25: Interest Expense | B25: =Overhead!$I$15/12 -> 1195.5828 | C25: =Overhead!$I$15/12 -> 1195.5828 | D25: =Overhead!$I$15/12 -> 1195.5828 | E25: =Overhead!$I$15/12 -> 1195.5828 | F25: =Overhead!$I$15/12 -> 1195.5828 | G25: =Overhead!$I$15/12 -> 1195.5828 | H25: =Overhead!$I$15/12 -> 1195.5828 | I25: =Overhead!$I$15/12 -> 1195.5828 | ... M25: =Overhead!$I$15/12 -> 1195.5828 | N25: =SUM(B25:M25) -> 14346.994 | O25: =Overhead!F15 -> 13929.12 | P25: =N25-O25 -> 417.8736 | Q25: =IF(O25=0,"",N25/O25-1) -> 0.03
A27: Total expenses | B27: =B14+B21+B25 -> 66201.64 | C27: =C14+C21+C25 -> 66201.64 | D27: =D14+D21+D25 -> 66201.64 | E27: =E14+E21+E25 -> 66201.64 | F27: =F14+F21+F25 -> 66201.64 | G27: =G14+G21+G25 -> 66201.64 | H27: =H14+H21+H25 -> 76201.64 | I27: =I14+I21+I25 -> 76201.64 | ... M27: =M14+M21+M25 -> 196201.64 | N27: =SUM(B27:M27) -> 974419.68 | O27: =SUMIFS(Overhead!$F$5:$F$16,Overhead!$A$5:$A$16,"COGS",Overhead!$E$5:$E$16,"<>Exclude")+SUMIFS(Overhead!$F$5:$F$16,Overhead!$A$5:$A$16,"Expense",Overhead!$E$5:$E$16,"<>Exclude")+SUMIFS(Overhead!$F$5:$F$16,Overhead!$A$5:$A$16,"Other Expense",Overhead!$E$5:$E$16,"<>Exclude") -> 2556599 | P27: =N27-O27 -> -1582179.3 | Q27: =IF(O27=0,"",N27/O27-1) -> -0.61886096
A28: Net income before owner draws | B28: =B8+B24-B27 -> 170759.12 | C28: =C8+C24-C27 -> 159734.12 | D28: =D8+D24-D27 -> 192809.12 | E28: =E8+E24-E27 -> 181784.12 | F28: =F8+F24-F27 -> 170759.12 | G28: =G8+G24-G27 -> 181784.12 | H28: =H8+H24-H27 -> 171784.12 | I28: =I8+I24-I27 -> 171784.12 | ... M28: =M8+M24-M27 -> 62809.119 | N28: =SUM(B28:M28) -> 1968334.4 | O28: =SUMIFS(Overhead!$F$5:$F$16,Overhead!$A$5:$A$16,"Revenue",Overhead!$E$5:$E$16,"<>Exclude")+SUMIFS(Overhead!$F$5:$F$16,Overhead!$A$5:$A$16,"Other Income",Overhead!$E$5:$E$16,"<>Exclude")-SUMIFS(Overhead!$F$5:$F$16,Overhead!$A$5:$A$16,"COGS",Overhead!$E$5:$E$16,"<>Exclude")-SUMIFS(Overhead!$F$5:$F$16,Overhead!$A$5:$A$16,"Expense",Overhead!$E$5:$E$16,"<>Exclude")-SUMIFS(Overhead!$F$5:$F$16,Overhead!$A$5:$A$16,"Other Expense",Overhead!$E$5:$E$16,"<>Exclude") -> 2531517.5 | P28: =N28-O28 -> -563183.06 | Q28: =IF(O28=0,"",N28/O28-1) -> -0.22246856
A29: Net margin | B29: =IF(B8=0,0,B28/B8) -> 0.72220527 | C29: =IF(C8=0,0,C28/C8) -> 0.70861846 | D29: =IF(D8=0,0,D28/D8) -> 0.74590191 | E29: =IF(E8=0,0,E28/E8) -> 0.73458145 | F29: =IF(F8=0,0,F28/F8) -> 0.72220527 | G29: =IF(G8=0,0,G28/G8) -> 0.73458145 | H29: =IF(H8=0,0,H28/H8) -> 0.6941719 | I29: =IF(I8=0,0,I28/I8) -> 0.6941719 | ... N29: =IF(N8=0,0,N28/N8) -> 0.67029491
A31: Owner draws
A32: Owner draw - Partner A | B32: =Drivers!K5 -> 100000 | C32: =Drivers!L5 -> 100000 | D32: =Drivers!M5 -> 100000 | E32: =Drivers!N5 -> 100000 | F32: =Drivers!O5 -> 100000 | G32: =Drivers!P5 -> 100000 | H32: =Drivers!Q5 -> 100000 | I32: =Drivers!R5 -> 100000 | ... M32: =Drivers!V5 -> 100000 | N32: =SUM(B32:M32) -> 1200000
A33: Owner draw - Partner B | B33: =Drivers!K6 -> 30000 | C33: =Drivers!L6 -> 30000 | D33: =Drivers!M6 -> 30000 | E33: =Drivers!N6 -> 30000 | F33: =Drivers!O6 -> 30000 | G33: =Drivers!P6 -> 30000 | H33: =Drivers!Q6 -> 30000 | I33: =Drivers!R6 -> 30000 | ... M33: =Drivers!V6 -> 30000 | N33: =SUM(B33:M33) -> 360000
A34: Total owner draws | B34: =B32+B33 -> 130000 | C34: =C32+C33 -> 130000 | D34: =D32+D33 -> 130000 | E34: =E32+E33 -> 130000 | F34: =F32+F33 -> 130000 | G34: =G32+G33 -> 130000 | H34: =H32+H33 -> 130000 | I34: =I32+I33 -> 130000 | ... M34: =M32+M33 -> 130000 | N34: =SUM(B34:M34) -> 1560000
A35: Remaining after owner draws | B35: =B28-B34 -> 40759.119 | C35: =C28-C34 -> 29734.119 | D35: =D28-D34 -> 62809.119 | E35: =E28-E34 -> 51784.119 | F35: =F28-F34 -> 40759.119 | G35: =G28-G34 -> 51784.119 | H35: =H28-H34 -> 41784.119 | I35: =I28-I34 -> 41784.119 | ... M35: =M28-M34 -> -67190.881 | N35: =SUM(B35:M35) -> 408334.43
A37: Check: drivers not on the P&L (should be 0) | N37: =SUM(Drivers!I5:I9)-(SUMIFS(Drivers!I$5:I$9,Drivers!$C$5:$C$9,"Owner draws")+SUMIFS(Drivers!I$5:I$9,Drivers!$C$5:$C$9,"Personnel")+SUMIFS(Drivers!I$5:I$9,Drivers!$C$5:$C$9,"Operating expense")+SUMIFS(Drivers!I$5:I$9,Drivers!$C$5:$C$9,"Other expense")+SUMIFS(Drivers!I$5:I$9,Drivers!$C$5:$C$9,"Revenue")+SUMIFS(Drivers!I$5:I$9,Drivers!$C$5:$C$9,"Other income")) -> 0

Sheet Assumptions
A1: Assumptions
A3: Assumption | B3: Value | C3: Note
A4: Budget year | B4: 2027 | C4: Calendar year
A5: Billing rate increase | B5: 0.05 | C5: Applied to every person's rate
A6: Rate increase month (1-12) | B6: 1 | C6: New rates apply from this month
A7: Salary increase | B7: 0.03 | C7: Annual raise
A8: Salary increase month (1-12) | B8: 1 | C8: Raises apply from this month
A9: Payroll taxes & benefits (fringe) | B9: 0.164 | C9: On top of salaries. Fringe only, not overhead.
A10: Default realization | B10: 0.9 | C10: Billed / standard value, for new people rows
A11: Default overhead change | B11: 0.03 | C11: For prior-year overhead lines
A14: Seasonality (share of annual billable hours by month)
A15: Default = share of Mon-Fri workdays. Must total 100%.
A16: Jan | B16: 0.08045977
A17: Feb | B17: 0.076628352
A18: Mar | B18: 0.088122605
A19: Apr | B19: 0.084291188
A20: May | B20: 0.08045977
A21: Jun | B21: 0.084291188
A22: Jul | B22: 0.084291188
A23: Aug | B23: 0.084291188
A24: Sep | B24: 0.084291188
A25: Oct | B25: 0.08045977
A26: Nov | B26: 0.084291188
A27: Dec | B27: 0.088122605
A28: Total | B28: =SUM(B16:B27) -> 1 | C28: =IF(ABS(B28-1)>0.0001,"Check: weights should total 100%","OK") -> OK

Sheet People
A1: People plan
A2: Example of a new hire row: Y | New Associate | Attorney | 4 | 12 | 150000 | 1900 | 325 | 90%
A4: Include (Y/N) | B4: Name | C4: Role | D4: Start month | E4: End month | F4: Annual salary ($) | G4: Billable hours (annual) | H4: Billing rate ($/hr) | I4: Realization | J4: Budget revenue ($) | K4: Salary + fringe ($) | L4: Contribution ($) | M4: Prior billable hours | N4: Prior rate ($/hr) | O4: Note
A5: Y | B5: Ann Associate | C5: Attorney | D5: 1 | E5: 12 | F5: 150000 | G5: 1900 | H5: 350 | I5: 0.9 | J5: =SUM('Revenue by Person'!C5:N5) -> 628425 | K5: =SUM('Salary by Person'!C5:N5)*(1+Assumptions!$B$9) -> 179838 | L5: =J5-K5 -> 448587 | M5: 1800 | N5: 350
A6: Y | B6: Paul Planner | C6: Planner | D6: 1 | E6: 12 | F6: 114000 | G6: 1600 | H6: 250 | I6: 0.9 | J6: =SUM('Revenue by Person'!C6:N6) -> 378000 | K6: =SUM('Salary by Person'!C6:N6)*(1+Assumptions!$B$9) -> 136676.88 | L6: =J6-K6 -> 241323.12 | M6: 1500 | N6: 250
A7: Y | B7: Kim Lee | C7: Principal | D7: 1 | E7: 12 | F7: 0 | G7: 1500 | H7: 600 | I7: 0.9 | J7: =SUM('Revenue by Person'!C7:N7) -> 850500 | K7: =SUM('Salary by Person'!C7:N7)*(1+Assumptions!$B$9) -> 0 | L7: =J7-K7 -> 850500 | M7: 1500 | N7: 600 | O7: Paid by owner draw (Budget drivers)
A8: Y | B8: Pat Owner Jr. | C8: Principal | D8: 1 | E8: 12 | F8: 0 | G8: 1200 | H8: 900 | I8: 0.9 | J8: =SUM('Revenue by Person'!C8:N8) -> 1020600 | K8: =SUM('Salary by Person'!C8:N8)*(1+Assumptions!$B$9) -> 0 | L8: =J8-K8 -> 1020600 | M8: 1200 | N8: 900 | O8: Paid by owner draw (Budget drivers)
A9: N | B9: Sam Staff | C9: Employee | D9: 1 | E9: 12 | F9: 60000 | G9: 0 | H9: 0 | I9: 0.9 | J9: =SUM('Revenue by Person'!C9:N9) -> 0 | K9: =SUM('Salary by Person'!C9:N9)*(1+Assumptions!$B$9) -> 0 | L9: =J9-K9 -> 0
B11: Total | F11: =SUM(F5:F10) -> 324000 | G11: =SUM(G5:G10) -> 6200 | J11: =SUM(J5:J10) -> 2877525 | K11: =SUM(K5:K10) -> 316514.88 | L11: =SUM(L5:L10) -> 2561010.1

Sheet Revenue by Person
A1: Revenue by Person (hours x weight x rate x realization)
C3: 1 | D3: 2 | E3: 3 | F3: 4 | G3: 5 | H3: 6 | I3: 7 | J3: 8 | K3: 9 | L3: 10 | M3: 11 | N3: 12
A4: Name | B4: Total | C4: Jan | D4: Feb | E4: Mar | F4: Apr | G4: May | H4: Jun | I4: Jul | J4: Aug | K4: Sep | L4: Oct | M4: Nov | N4: Dec
A5: =IF(People!B5="","",People!B5) -> Ann Associate | B5: =SUM(C5:N5) -> 628425 | C5: =IF(AND(People!$A5="Y",C$3>=People!$D5,C$3<=People!$E5),People!$G5*INDEX(Assumptions!$B$16:$B$27,C$3)/Assumptions!$B$28*People!$H5*IF(C$3>=Assumptions!$B$6,1+Assumptions!$B$5,1)*People!$I5,0) -> 50562.931 | D5: =IF(AND(People!$A5="Y",D$3>=People!$D5,D$3<=People!$E5),People!$G5*INDEX(Assumptions!$B$16:$B$27,D$3)/Assumptions!$B$28*People!$H5*IF(D$3>=Assumptions!$B$6,1+Assumptions!$B$5,1)*People!$I5,0) -> 48155.172 | E5: =IF(AND(People!$A5="Y",E$3>=People!$D5,E$3<=People!$E5),People!$G5*INDEX(Assumptions!$B$16:$B$27,E$3)/Assumptions!$B$28*People!$H5*IF(E$3>=Assumptions!$B$6,1+Assumptions!$B$5,1)*People!$I5,0) -> 55378.448 | F5: =IF(AND(People!$A5="Y",F$3>=People!$D5,F$3<=People!$E5),People!$G5*INDEX(Assumptions!$B$16:$B$27,F$3)/Assumptions!$B$28*People!$H5*IF(F$3>=Assumptions!$B$6,1+Assumptions!$B$5,1)*People!$I5,0) -> 52970.69 | G5: =IF(AND(People!$A5="Y",G$3>=People!$D5,G$3<=People!$E5),People!$G5*INDEX(Assumptions!$B$16:$B$27,G$3)/Assumptions!$B$28*People!$H5*IF(G$3>=Assumptions!$B$6,1+Assumptions!$B$5,1)*People!$I5,0) -> 50562.931 | H5: =IF(AND(People!$A5="Y",H$3>=People!$D5,H$3<=People!$E5),People!$G5*INDEX(Assumptions!$B$16:$B$27,H$3)/Assumptions!$B$28*People!$H5*IF(H$3>=Assumptions!$B$6,1+Assumptions!$B$5,1)*People!$I5,0) -> 52970.69 | I5: =IF(AND(People!$A5="Y",I$3>=People!$D5,I$3<=People!$E5),People!$G5*INDEX(Assumptions!$B$16:$B$27,I$3)/Assumptions!$B$28*People!$H5*IF(I$3>=Assumptions!$B$6,1+Assumptions!$B$5,1)*People!$I5,0) -> 52970.69 | J5: =IF(AND(People!$A5="Y",J$3>=People!$D5,J$3<=People!$E5),People!$G5*INDEX(Assumptions!$B$16:$B$27,J$3)/Assumptions!$B$28*People!$H5*IF(J$3>=Assumptions!$B$6,1+Assumptions!$B$5,1)*People!$I5,0) -> 52970.69 | ... N5: =IF(AND(People!$A5="Y",N$3>=People!$D5,N$3<=People!$E5),People!$G5*INDEX(Assumptions!$B$16:$B$27,N$3)/Assumptions!$B$28*People!$H5*IF(N$3>=Assumptions!$B$6,1+Assumptions!$B$5,1)*People!$I5,0) -> 55378.448
A6: =IF(People!B6="","",People!B6) -> Paul Planner | B6: =SUM(C6:N6) -> 378000 | C6: =IF(AND(People!$A6="Y",C$3>=People!$D6,C$3<=People!$E6),People!$G6*INDEX(Assumptions!$B$16:$B$27,C$3)/Assumptions!$B$28*People!$H6*IF(C$3>=Assumptions!$B$6,1+Assumptions!$B$5,1)*People!$I6,0) -> 30413.793 | D6: =IF(AND(People!$A6="Y",D$3>=People!$D6,D$3<=People!$E6),People!$G6*INDEX(Assumptions!$B$16:$B$27,D$3)/Assumptions!$B$28*People!$H6*IF(D$3>=Assumptions!$B$6,1+Assumptions!$B$5,1)*People!$I6,0) -> 28965.517 | E6: =IF(AND(People!$A6="Y",E$3>=People!$D6,E$3<=People!$E6),People!$G6*INDEX(Assumptions!$B$16:$B$27,E$3)/Assumptions!$B$28*People!$H6*IF(E$3>=Assumptions!$B$6,1+Assumptions!$B$5,1)*People!$I6,0) -> 33310.345 | F6: =IF(AND(People!$A6="Y",F$3>=People!$D6,F$3<=People!$E6),People!$G6*INDEX(Assumptions!$B$16:$B$27,F$3)/Assumptions!$B$28*People!$H6*IF(F$3>=Assumptions!$B$6,1+Assumptions!$B$5,1)*People!$I6,0) -> 31862.069 | G6: =IF(AND(People!$A6="Y",G$3>=People!$D6,G$3<=People!$E6),People!$G6*INDEX(Assumptions!$B$16:$B$27,G$3)/Assumptions!$B$28*People!$H6*IF(G$3>=Assumptions!$B$6,1+Assumptions!$B$5,1)*People!$I6,0) -> 30413.793 | H6: =IF(AND(People!$A6="Y",H$3>=People!$D6,H$3<=People!$E6),People!$G6*INDEX(Assumptions!$B$16:$B$27,H$3)/Assumptions!$B$28*People!$H6*IF(H$3>=Assumptions!$B$6,1+Assumptions!$B$5,1)*People!$I6,0) -> 31862.069 | I6: =IF(AND(People!$A6="Y",I$3>=People!$D6,I$3<=People!$E6),People!$G6*INDEX(Assumptions!$B$16:$B$27,I$3)/Assumptions!$B$28*People!$H6*IF(I$3>=Assumptions!$B$6,1+Assumptions!$B$5,1)*People!$I6,0) -> 31862.069 | J6: =IF(AND(People!$A6="Y",J$3>=People!$D6,J$3<=People!$E6),People!$G6*INDEX(Assumptions!$B$16:$B$27,J$3)/Assumptions!$B$28*People!$H6*IF(J$3>=Assumptions!$B$6,1+Assumptions!$B$5,1)*People!$I6,0) -> 31862.069 | ... N6: =IF(AND(People!$A6="Y",N$3>=People!$D6,N$3<=People!$E6),People!$G6*INDEX(Assumptions!$B$16:$B$27,N$3)/Assumptions!$B$28*People!$H6*IF(N$3>=Assumptions!$B$6,1+Assumptions!$B$5,1)*People!$I6,0) -> 33310.345
A7: =IF(People!B7="","",People!B7) -> Kim Lee | B7: =SUM(C7:N7) -> 850500 | C7: =IF(AND(People!$A7="Y",C$3>=People!$D7,C$3<=People!$E7),People!$G7*INDEX(Assumptions!$B$16:$B$27,C$3)/Assumptions!$B$28*People!$H7*IF(C$3>=Assumptions!$B$6,1+Assumptions!$B$5,1)*People!$I7,0) -> 68431.034 | D7: =IF(AND(People!$A7="Y",D$3>=People!$D7,D$3<=People!$E7),People!$G7*INDEX(Assumptions!$B$16:$B$27,D$3)/Assumptions!$B$28*People!$H7*IF(D$3>=Assumptions!$B$6,1+Assumptions!$B$5,1)*People!$I7,0) -> 65172.414 | E7: =IF(AND(People!$A7="Y",E$3>=People!$D7,E$3<=People!$E7),People!$G7*INDEX(Assumptions!$B$16:$B$27,E$3)/Assumptions!$B$28*People!$H7*IF(E$3>=Assumptions!$B$6,1+Assumptions!$B$5,1)*People!$I7,0) -> 74948.276 | F7: =IF(AND(People!$A7="Y",F$3>=People!$D7,F$3<=People!$E7),People!$G7*INDEX(Assumptions!$B$16:$B$27,F$3)/Assumptions!$B$28*People!$H7*IF(F$3>=Assumptions!$B$6,1+Assumptions!$B$5,1)*People!$I7,0) -> 71689.655 | G7: =IF(AND(People!$A7="Y",G$3>=People!$D7,G$3<=People!$E7),People!$G7*INDEX(Assumptions!$B$16:$B$27,G$3)/Assumptions!$B$28*People!$H7*IF(G$3>=Assumptions!$B$6,1+Assumptions!$B$5,1)*People!$I7,0) -> 68431.034 | H7: =IF(AND(People!$A7="Y",H$3>=People!$D7,H$3<=People!$E7),People!$G7*INDEX(Assumptions!$B$16:$B$27,H$3)/Assumptions!$B$28*People!$H7*IF(H$3>=Assumptions!$B$6,1+Assumptions!$B$5,1)*People!$I7,0) -> 71689.655 | I7: =IF(AND(People!$A7="Y",I$3>=People!$D7,I$3<=People!$E7),People!$G7*INDEX(Assumptions!$B$16:$B$27,I$3)/Assumptions!$B$28*People!$H7*IF(I$3>=Assumptions!$B$6,1+Assumptions!$B$5,1)*People!$I7,0) -> 71689.655 | J7: =IF(AND(People!$A7="Y",J$3>=People!$D7,J$3<=People!$E7),People!$G7*INDEX(Assumptions!$B$16:$B$27,J$3)/Assumptions!$B$28*People!$H7*IF(J$3>=Assumptions!$B$6,1+Assumptions!$B$5,1)*People!$I7,0) -> 71689.655 | ... N7: =IF(AND(People!$A7="Y",N$3>=People!$D7,N$3<=People!$E7),People!$G7*INDEX(Assumptions!$B$16:$B$27,N$3)/Assumptions!$B$28*People!$H7*IF(N$3>=Assumptions!$B$6,1+Assumptions!$B$5,1)*People!$I7,0) -> 74948.276
A8: =IF(People!B8="","",People!B8) -> Pat Owner Jr. | B8: =SUM(C8:N8) -> 1020600 | C8: =IF(AND(People!$A8="Y",C$3>=People!$D8,C$3<=People!$E8),People!$G8*INDEX(Assumptions!$B$16:$B$27,C$3)/Assumptions!$B$28*People!$H8*IF(C$3>=Assumptions!$B$6,1+Assumptions!$B$5,1)*People!$I8,0) -> 82117.241 | D8: =IF(AND(People!$A8="Y",D$3>=People!$D8,D$3<=People!$E8),People!$G8*INDEX(Assumptions!$B$16:$B$27,D$3)/Assumptions!$B$28*People!$H8*IF(D$3>=Assumptions!$B$6,1+Assumptions!$B$5,1)*People!$I8,0) -> 78206.897 | E8: =IF(AND(People!$A8="Y",E$3>=People!$D8,E$3<=People!$E8),People!$G8*INDEX(Assumptions!$B$16:$B$27,E$3)/Assumptions!$B$28*People!$H8*IF(E$3>=Assumptions!$B$6,1+Assumptions!$B$5,1)*People!$I8,0) -> 89937.931 | F8: =IF(AND(People!$A8="Y",F$3>=People!$D8,F$3<=People!$E8),People!$G8*INDEX(Assumptions!$B$16:$B$27,F$3)/Assumptions!$B$28*People!$H8*IF(F$3>=Assumptions!$B$6,1+Assumptions!$B$5,1)*People!$I8,0) -> 86027.586 | G8: =IF(AND(People!$A8="Y",G$3>=People!$D8,G$3<=People!$E8),People!$G8*INDEX(Assumptions!$B$16:$B$27,G$3)/Assumptions!$B$28*People!$H8*IF(G$3>=Assumptions!$B$6,1+Assumptions!$B$5,1)*People!$I8,0) -> 82117.241 | H8: =IF(AND(People!$A8="Y",H$3>=People!$D8,H$3<=People!$E8),People!$G8*INDEX(Assumptions!$B$16:$B$27,H$3)/Assumptions!$B$28*People!$H8*IF(H$3>=Assumptions!$B$6,1+Assumptions!$B$5,1)*People!$I8,0) -> 86027.586 | I8: =IF(AND(People!$A8="Y",I$3>=People!$D8,I$3<=People!$E8),People!$G8*INDEX(Assumptions!$B$16:$B$27,I$3)/Assumptions!$B$28*People!$H8*IF(I$3>=Assumptions!$B$6,1+Assumptions!$B$5,1)*People!$I8,0) -> 86027.586 | J8: =IF(AND(People!$A8="Y",J$3>=People!$D8,J$3<=People!$E8),People!$G8*INDEX(Assumptions!$B$16:$B$27,J$3)/Assumptions!$B$28*People!$H8*IF(J$3>=Assumptions!$B$6,1+Assumptions!$B$5,1)*People!$I8,0) -> 86027.586 | ... N8: =IF(AND(People!$A8="Y",N$3>=People!$D8,N$3<=People!$E8),People!$G8*INDEX(Assumptions!$B$16:$B$27,N$3)/Assumptions!$B$28*People!$H8*IF(N$3>=Assumptions!$B$6,1+Assumptions!$B$5,1)*People!$I8,0) -> 89937.931
A9: =IF(People!B9="","",People!B9) -> Sam Staff | B9: =SUM(C9:N9) -> 0 | C9: =IF(AND(People!$A9="Y",C$3>=People!$D9,C$3<=People!$E9),People!$G9*INDEX(Assumptions!$B$16:$B$27,C$3)/Assumptions!$B$28*People!$H9*IF(C$3>=Assumptions!$B$6,1+Assumptions!$B$5,1)*People!$I9,0) -> 0 | D9: =IF(AND(People!$A9="Y",D$3>=People!$D9,D$3<=People!$E9),People!$G9*INDEX(Assumptions!$B$16:$B$27,D$3)/Assumptions!$B$28*People!$H9*IF(D$3>=Assumptions!$B$6,1+Assumptions!$B$5,1)*People!$I9,0) -> 0 | E9: =IF(AND(People!$A9="Y",E$3>=People!$D9,E$3<=People!$E9),People!$G9*INDEX(Assumptions!$B$16:$B$27,E$3)/Assumptions!$B$28*People!$H9*IF(E$3>=Assumptions!$B$6,1+Assumptions!$B$5,1)*People!$I9,0) -> 0 | F9: =IF(AND(People!$A9="Y",F$3>=People!$D9,F$3<=People!$E9),People!$G9*INDEX(Assumptions!$B$16:$B$27,F$3)/Assumptions!$B$28*People!$H9*IF(F$3>=Assumptions!$B$6,1+Assumptions!$B$5,1)*People!$I9,0) -> 0 | G9: =IF(AND(People!$A9="Y",G$3>=People!$D9,G$3<=People!$E9),People!$G9*INDEX(Assumptions!$B$16:$B$27,G$3)/Assumptions!$B$28*People!$H9*IF(G$3>=Assumptions!$B$6,1+Assumptions!$B$5,1)*People!$I9,0) -> 0 | H9: =IF(AND(People!$A9="Y",H$3>=People!$D9,H$3<=People!$E9),People!$G9*INDEX(Assumptions!$B$16:$B$27,H$3)/Assumptions!$B$28*People!$H9*IF(H$3>=Assumptions!$B$6,1+Assumptions!$B$5,1)*People!$I9,0) -> 0 | I9: =IF(AND(People!$A9="Y",I$3>=People!$D9,I$3<=People!$E9),People!$G9*INDEX(Assumptions!$B$16:$B$27,I$3)/Assumptions!$B$28*People!$H9*IF(I$3>=Assumptions!$B$6,1+Assumptions!$B$5,1)*People!$I9,0) -> 0 | J9: =IF(AND(People!$A9="Y",J$3>=People!$D9,J$3<=People!$E9),People!$G9*INDEX(Assumptions!$B$16:$B$27,J$3)/Assumptions!$B$28*People!$H9*IF(J$3>=Assumptions!$B$6,1+Assumptions!$B$5,1)*People!$I9,0) -> 0 | ... N9: =IF(AND(People!$A9="Y",N$3>=People!$D9,N$3<=People!$E9),People!$G9*INDEX(Assumptions!$B$16:$B$27,N$3)/Assumptions!$B$28*People!$H9*IF(N$3>=Assumptions!$B$6,1+Assumptions!$B$5,1)*People!$I9,0) -> 0
A10: =IF(People!B10="","",People!B10) | B10: =SUM(C10:N10) -> 0 | C10: =IF(AND(People!$A10="Y",C$3>=People!$D10,C$3<=People!$E10),People!$G10*INDEX(Assumptions!$B$16:$B$27,C$3)/Assumptions!$B$28*People!$H10*IF(C$3>=Assumptions!$B$6,1+Assumptions!$B$5,1)*People!$I10,0) -> 0 | D10: =IF(AND(People!$A10="Y",D$3>=People!$D10,D$3<=People!$E10),People!$G10*INDEX(Assumptions!$B$16:$B$27,D$3)/Assumptions!$B$28*People!$H10*IF(D$3>=Assumptions!$B$6,1+Assumptions!$B$5,1)*People!$I10,0) -> 0 | E10: =IF(AND(People!$A10="Y",E$3>=People!$D10,E$3<=People!$E10),People!$G10*INDEX(Assumptions!$B$16:$B$27,E$3)/Assumptions!$B$28*People!$H10*IF(E$3>=Assumptions!$B$6,1+Assumptions!$B$5,1)*People!$I10,0) -> 0 | F10: =IF(AND(People!$A10="Y",F$3>=People!$D10,F$3<=People!$E10),People!$G10*INDEX(Assumptions!$B$16:$B$27,F$3)/Assumptions!$B$28*People!$H10*IF(F$3>=Assumptions!$B$6,1+Assumptions!$B$5,1)*People!$I10,0) -> 0 | G10: =IF(AND(People!$A10="Y",G$3>=People!$D10,G$3<=People!$E10),People!$G10*INDEX(Assumptions!$B$16:$B$27,G$3)/Assumptions!$B$28*People!$H10*IF(G$3>=Assumptions!$B$6,1+Assumptions!$B$5,1)*People!$I10,0) -> 0 | H10: =IF(AND(People!$A10="Y",H$3>=People!$D10,H$3<=People!$E10),People!$G10*INDEX(Assumptions!$B$16:$B$27,H$3)/Assumptions!$B$28*People!$H10*IF(H$3>=Assumptions!$B$6,1+Assumptions!$B$5,1)*People!$I10,0) -> 0 | I10: =IF(AND(People!$A10="Y",I$3>=People!$D10,I$3<=People!$E10),People!$G10*INDEX(Assumptions!$B$16:$B$27,I$3)/Assumptions!$B$28*People!$H10*IF(I$3>=Assumptions!$B$6,1+Assumptions!$B$5,1)*People!$I10,0) -> 0 | J10: =IF(AND(People!$A10="Y",J$3>=People!$D10,J$3<=People!$E10),People!$G10*INDEX(Assumptions!$B$16:$B$27,J$3)/Assumptions!$B$28*People!$H10*IF(J$3>=Assumptions!$B$6,1+Assumptions!$B$5,1)*People!$I10,0) -> 0 | ... N10: =IF(AND(People!$A10="Y",N$3>=People!$D10,N$3<=People!$E10),People!$G10*INDEX(Assumptions!$B$16:$B$27,N$3)/Assumptions!$B$28*People!$H10*IF(N$3>=Assumptions!$B$6,1+Assumptions!$B$5,1)*People!$I10,0) -> 0
A11: Total | B11: =SUM(B5:B10) -> 2877525 | C11: =SUM(C5:C10) -> 231525 | D11: =SUM(D5:D10) -> 220500 | E11: =SUM(E5:E10) -> 253575 | F11: =SUM(F5:F10) -> 242550 | G11: =SUM(G5:G10) -> 231525 | H11: =SUM(H5:H10) -> 242550 | I11: =SUM(I5:I10) -> 242550 | ... N11: =SUM(N5:N10) -> 253575

Sheet Salary by Person
A1: Salary by Person (before fringe)
C3: 1 | D3: 2 | E3: 3 | F3: 4 | G3: 5 | H3: 6 | I3: 7 | J3: 8 | K3: 9 | L3: 10 | M3: 11 | N3: 12
A4: Name | B4: Total | C4: Jan | D4: Feb | E4: Mar | F4: Apr | G4: May | H4: Jun | I4: Jul | J4: Aug | K4: Sep | L4: Oct | M4: Nov | N4: Dec
A5: =IF(People!B5="","",People!B5) -> Ann Associate | B5: =SUM(C5:N5) -> 154500 | C5: =IF(AND(People!$A5="Y",C$3>=People!$D5,C$3<=People!$E5),People!$F5/12*IF(C$3>=Assumptions!$B$8,1+Assumptions!$B$7,1),0) -> 12875 | D5: =IF(AND(People!$A5="Y",D$3>=People!$D5,D$3<=People!$E5),People!$F5/12*IF(D$3>=Assumptions!$B$8,1+Assumptions!$B$7,1),0) -> 12875 | E5: =IF(AND(People!$A5="Y",E$3>=People!$D5,E$3<=People!$E5),People!$F5/12*IF(E$3>=Assumptions!$B$8,1+Assumptions!$B$7,1),0) -> 12875 | F5: =IF(AND(People!$A5="Y",F$3>=People!$D5,F$3<=People!$E5),People!$F5/12*IF(F$3>=Assumptions!$B$8,1+Assumptions!$B$7,1),0) -> 12875 | G5: =IF(AND(People!$A5="Y",G$3>=People!$D5,G$3<=People!$E5),People!$F5/12*IF(G$3>=Assumptions!$B$8,1+Assumptions!$B$7,1),0) -> 12875 | H5: =IF(AND(People!$A5="Y",H$3>=People!$D5,H$3<=People!$E5),People!$F5/12*IF(H$3>=Assumptions!$B$8,1+Assumptions!$B$7,1),0) -> 12875 | I5: =IF(AND(People!$A5="Y",I$3>=People!$D5,I$3<=People!$E5),People!$F5/12*IF(I$3>=Assumptions!$B$8,1+Assumptions!$B$7,1),0) -> 12875 | J5: =IF(AND(People!$A5="Y",J$3>=People!$D5,J$3<=People!$E5),People!$F5/12*IF(J$3>=Assumptions!$B$8,1+Assumptions!$B$7,1),0) -> 12875 | ... N5: =IF(AND(People!$A5="Y",N$3>=People!$D5,N$3<=People!$E5),People!$F5/12*IF(N$3>=Assumptions!$B$8,1+Assumptions!$B$7,1),0) -> 12875
A6: =IF(People!B6="","",People!B6) -> Paul Planner | B6: =SUM(C6:N6) -> 117420 | C6: =IF(AND(People!$A6="Y",C$3>=People!$D6,C$3<=People!$E6),People!$F6/12*IF(C$3>=Assumptions!$B$8,1+Assumptions!$B$7,1),0) -> 9785 | D6: =IF(AND(People!$A6="Y",D$3>=People!$D6,D$3<=People!$E6),People!$F6/12*IF(D$3>=Assumptions!$B$8,1+Assumptions!$B$7,1),0) -> 9785 | E6: =IF(AND(People!$A6="Y",E$3>=People!$D6,E$3<=People!$E6),People!$F6/12*IF(E$3>=Assumptions!$B$8,1+Assumptions!$B$7,1),0) -> 9785 | F6: =IF(AND(People!$A6="Y",F$3>=People!$D6,F$3<=People!$E6),People!$F6/12*IF(F$3>=Assumptions!$B$8,1+Assumptions!$B$7,1),0) -> 9785 | G6: =IF(AND(People!$A6="Y",G$3>=People!$D6,G$3<=People!$E6),People!$F6/12*IF(G$3>=Assumptions!$B$8,1+Assumptions!$B$7,1),0) -> 9785 | H6: =IF(AND(People!$A6="Y",H$3>=People!$D6,H$3<=People!$E6),People!$F6/12*IF(H$3>=Assumptions!$B$8,1+Assumptions!$B$7,1),0) -> 9785 | I6: =IF(AND(People!$A6="Y",I$3>=People!$D6,I$3<=People!$E6),People!$F6/12*IF(I$3>=Assumptions!$B$8,1+Assumptions!$B$7,1),0) -> 9785 | J6: =IF(AND(People!$A6="Y",J$3>=People!$D6,J$3<=People!$E6),People!$F6/12*IF(J$3>=Assumptions!$B$8,1+Assumptions!$B$7,1),0) -> 9785 | ... N6: =IF(AND(People!$A6="Y",N$3>=People!$D6,N$3<=People!$E6),People!$F6/12*IF(N$3>=Assumptions!$B$8,1+Assumptions!$B$7,1),0) -> 9785
A7: =IF(People!B7="","",People!B7) -> Kim Lee | B7: =SUM(C7:N7) -> 0 | C7: =IF(AND(People!$A7="Y",C$3>=People!$D7,C$3<=People!$E7),People!$F7/12*IF(C$3>=Assumptions!$B$8,1+Assumptions!$B$7,1),0) -> 0 | D7: =IF(AND(People!$A7="Y",D$3>=People!$D7,D$3<=People!$E7),People!$F7/12*IF(D$3>=Assumptions!$B$8,1+Assumptions!$B$7,1),0) -> 0 | E7: =IF(AND(People!$A7="Y",E$3>=People!$D7,E$3<=People!$E7),People!$F7/12*IF(E$3>=Assumptions!$B$8,1+Assumptions!$B$7,1),0) -> 0 | F7: =IF(AND(People!$A7="Y",F$3>=People!$D7,F$3<=People!$E7),People!$F7/12*IF(F$3>=Assumptions!$B$8,1+Assumptions!$B$7,1),0) -> 0 | G7: =IF(AND(People!$A7="Y",G$3>=People!$D7,G$3<=People!$E7),People!$F7/12*IF(G$3>=Assumptions!$B$8,1+Assumptions!$B$7,1),0) -> 0 | H7: =IF(AND(People!$A7="Y",H$3>=People!$D7,H$3<=People!$E7),People!$F7/12*IF(H$3>=Assumptions!$B$8,1+Assumptions!$B$7,1),0) -> 0 | I7: =IF(AND(People!$A7="Y",I$3>=People!$D7,I$3<=People!$E7),People!$F7/12*IF(I$3>=Assumptions!$B$8,1+Assumptions!$B$7,1),0) -> 0 | J7: =IF(AND(People!$A7="Y",J$3>=People!$D7,J$3<=People!$E7),People!$F7/12*IF(J$3>=Assumptions!$B$8,1+Assumptions!$B$7,1),0) -> 0 | ... N7: =IF(AND(People!$A7="Y",N$3>=People!$D7,N$3<=People!$E7),People!$F7/12*IF(N$3>=Assumptions!$B$8,1+Assumptions!$B$7,1),0) -> 0
A8: =IF(People!B8="","",People!B8) -> Pat Owner Jr. | B8: =SUM(C8:N8) -> 0 | C8: =IF(AND(People!$A8="Y",C$3>=People!$D8,C$3<=People!$E8),People!$F8/12*IF(C$3>=Assumptions!$B$8,1+Assumptions!$B$7,1),0) -> 0 | D8: =IF(AND(People!$A8="Y",D$3>=People!$D8,D$3<=People!$E8),People!$F8/12*IF(D$3>=Assumptions!$B$8,1+Assumptions!$B$7,1),0) -> 0 | E8: =IF(AND(People!$A8="Y",E$3>=People!$D8,E$3<=People!$E8),People!$F8/12*IF(E$3>=Assumptions!$B$8,1+Assumptions!$B$7,1),0) -> 0 | F8: =IF(AND(People!$A8="Y",F$3>=People!$D8,F$3<=People!$E8),People!$F8/12*IF(F$3>=Assumptions!$B$8,1+Assumptions!$B$7,1),0) -> 0 | G8: =IF(AND(People!$A8="Y",G$3>=People!$D8,G$3<=People!$E8),People!$F8/12*IF(G$3>=Assumptions!$B$8,1+Assumptions!$B$7,1),0) -> 0 | H8: =IF(AND(People!$A8="Y",H$3>=People!$D8,H$3<=People!$E8),People!$F8/12*IF(H$3>=Assumptions!$B$8,1+Assumptions!$B$7,1),0) -> 0 | I8: =IF(AND(People!$A8="Y",I$3>=People!$D8,I$3<=People!$E8),People!$F8/12*IF(I$3>=Assumptions!$B$8,1+Assumptions!$B$7,1),0) -> 0 | J8: =IF(AND(People!$A8="Y",J$3>=People!$D8,J$3<=People!$E8),People!$F8/12*IF(J$3>=Assumptions!$B$8,1+Assumptions!$B$7,1),0) -> 0 | ... N8: =IF(AND(People!$A8="Y",N$3>=People!$D8,N$3<=People!$E8),People!$F8/12*IF(N$3>=Assumptions!$B$8,1+Assumptions!$B$7,1),0) -> 0
A9: =IF(People!B9="","",People!B9) -> Sam Staff | B9: =SUM(C9:N9) -> 0 | C9: =IF(AND(People!$A9="Y",C$3>=People!$D9,C$3<=People!$E9),People!$F9/12*IF(C$3>=Assumptions!$B$8,1+Assumptions!$B$7,1),0) -> 0 | D9: =IF(AND(People!$A9="Y",D$3>=People!$D9,D$3<=People!$E9),People!$F9/12*IF(D$3>=Assumptions!$B$8,1+Assumptions!$B$7,1),0) -> 0 | E9: =IF(AND(People!$A9="Y",E$3>=People!$D9,E$3<=People!$E9),People!$F9/12*IF(E$3>=Assumptions!$B$8,1+Assumptions!$B$7,1),0) -> 0 | F9: =IF(AND(People!$A9="Y",F$3>=People!$D9,F$3<=People!$E9),People!$F9/12*IF(F$3>=Assumptions!$B$8,1+Assumptions!$B$7,1),0) -> 0 | G9: =IF(AND(People!$A9="Y",G$3>=People!$D9,G$3<=People!$E9),People!$F9/12*IF(G$3>=Assumptions!$B$8,1+Assumptions!$B$7,1),0) -> 0 | H9: =IF(AND(People!$A9="Y",H$3>=People!$D9,H$3<=People!$E9),People!$F9/12*IF(H$3>=Assumptions!$B$8,1+Assumptions!$B$7,1),0) -> 0 | I9: =IF(AND(People!$A9="Y",I$3>=People!$D9,I$3<=People!$E9),People!$F9/12*IF(I$3>=Assumptions!$B$8,1+Assumptions!$B$7,1),0) -> 0 | J9: =IF(AND(People!$A9="Y",J$3>=People!$D9,J$3<=People!$E9),People!$F9/12*IF(J$3>=Assumptions!$B$8,1+Assumptions!$B$7,1),0) -> 0 | ... N9: =IF(AND(People!$A9="Y",N$3>=People!$D9,N$3<=People!$E9),People!$F9/12*IF(N$3>=Assumptions!$B$8,1+Assumptions!$B$7,1),0) -> 0
A10: =IF(People!B10="","",People!B10) | B10: =SUM(C10:N10) -> 0 | C10: =IF(AND(People!$A10="Y",C$3>=People!$D10,C$3<=People!$E10),People!$F10/12*IF(C$3>=Assumptions!$B$8,1+Assumptions!$B$7,1),0) -> 0 | D10: =IF(AND(People!$A10="Y",D$3>=People!$D10,D$3<=People!$E10),People!$F10/12*IF(D$3>=Assumptions!$B$8,1+Assumptions!$B$7,1),0) -> 0 | E10: =IF(AND(People!$A10="Y",E$3>=People!$D10,E$3<=People!$E10),People!$F10/12*IF(E$3>=Assumptions!$B$8,1+Assumptions!$B$7,1),0) -> 0 | F10: =IF(AND(People!$A10="Y",F$3>=People!$D10,F$3<=People!$E10),People!$F10/12*IF(F$3>=Assumptions!$B$8,1+Assumptions!$B$7,1),0) -> 0 | G10: =IF(AND(People!$A10="Y",G$3>=People!$D10,G$3<=People!$E10),People!$F10/12*IF(G$3>=Assumptions!$B$8,1+Assumptions!$B$7,1),0) -> 0 | H10: =IF(AND(People!$A10="Y",H$3>=People!$D10,H$3<=People!$E10),People!$F10/12*IF(H$3>=Assumptions!$B$8,1+Assumptions!$B$7,1),0) -> 0 | I10: =IF(AND(People!$A10="Y",I$3>=People!$D10,I$3<=People!$E10),People!$F10/12*IF(I$3>=Assumptions!$B$8,1+Assumptions!$B$7,1),0) -> 0 | J10: =IF(AND(People!$A10="Y",J$3>=People!$D10,J$3<=People!$E10),People!$F10/12*IF(J$3>=Assumptions!$B$8,1+Assumptions!$B$7,1),0) -> 0 | ... N10: =IF(AND(People!$A10="Y",N$3>=People!$D10,N$3<=People!$E10),People!$F10/12*IF(N$3>=Assumptions!$B$8,1+Assumptions!$B$7,1),0) -> 0
A11: Total | B11: =SUM(B5:B10) -> 271920 | C11: =SUM(C5:C10) -> 22660 | D11: =SUM(D5:D10) -> 22660 | E11: =SUM(E5:E10) -> 22660 | F11: =SUM(F5:F10) -> 22660 | G11: =SUM(G5:G10) -> 22660 | H11: =SUM(H5:H10) -> 22660 | I11: =SUM(I5:I10) -> 22660 | ... N11: =SUM(N5:N10) -> 22660

Sheet Overhead
A1: Prior-year lines (overhead and other)
A2: Treatment: 'Prior year + %' grows the line; 'People plan' replaces it with the people plan (fee revenue / payroll); 'Exclude' drops it. Fixed amount overrides Change %.
A4: Section | B4: Category | C4: Account | D4: Line item | E4: Treatment | F4: Prior year ($) | G4: Change % | H4: Fixed amount ($) | I4: Budget ($)
A5: Revenue | C5: 4000 | D5: Legal Fees | E5: People plan | F5: 3586597.4 | G5: 0.03 | I5: =IF(E5="Prior year + %",IF(H5<>"",H5,F5*(1+G5)),0) -> 0
A6: Revenue | C6: 4100 | D6: Planning Fees | E6: People plan | F6: 1438189.8 | G6: 0.03 | I6: =IF(E6="Prior year + %",IF(H6<>"",H6,F6*(1+G6)),0) -> 0
A7: Revenue | C7: 4900 | D7: Reimbursed Expenses | E7: Prior year + % | F7: 57276.75 | G7: 0.03 | I7: =IF(E7="Prior year + %",IF(H7<>"",H7,F7*(1+G7)),0) -> 58995.052
A8: Other Income | C8: 7000 | D8: Interest Income | E8: Prior year + % | F8: 6052.48 | G8: 0.03 | I8: =IF(E8="Prior year + %",IF(H8<>"",H8,F8*(1+G8)),0) -> 6234.0544
A9: Expense | B9: Payroll Expenses | C9: 6010 | D9: Salaries & Wages | E9: People plan | F9: 1839586 | G9: 0.03 | I9: =IF(E9="Prior year + %",IF(H9<>"",H9,F9*(1+G9)),0) -> 0
A10: Expense | B10: Payroll Expenses | C10: 6020 | D10: Payroll Taxes | E10: People plan | F10: 145687.76 | G10: 0.03 | I10: =IF(E10="Prior year + %",IF(H10<>"",H10,F10*(1+G10)),0) -> 0
A11: Expense | B11: Payroll Expenses | C11: 6030 | D11: Health Insurance | E11: People plan | F11: 107339.99 | G11: 0.03 | I11: =IF(E11="Prior year + %",IF(H11<>"",H11,F11*(1+G11)),0) -> 0
A12: Expense | C12: 6100 | D12: Rent | E12: Prior year + % | F12: 303870.57 | G12: 0.03 | I12: =IF(E12="Prior year + %",IF(H12<>"",H12,F12*(1+G12)),0) -> 312986.69
A13: Expense | C13: 6200 | D13: Software & Subscriptions | E13: Prior year + % | F13: 98422.55 | G13: 0.03 | I13: =IF(E13="Prior year + %",IF(H13<>"",H13,F13*(1+G13)),0) -> 101375.23
A14: Expense | C14: 6300 | D14: Professional Fees | E14: Prior year + % | F14: 47763 | G14: 0.03 | I14: =IF(E14="Prior year + %",IF(H14<>"",H14,F14*(1+G14)),0) -> 49195.89
A15: Other Expense | C15: 8000 | D15: Interest Expense | E15: Prior year + % | F15: 13929.12 | G15: 0.03 | I15: =IF(E15="Prior year + %",IF(H15<>"",H15,F15*(1+G15)),0) -> 14346.994
D17: Total | F17: =SUM(F5:F16) -> 7644715.4 | I17: =SUM(I5:I16) -> 543133.9

Sheet Drivers
A1: Budget drivers (owner draws, guaranteed payments, bonuses, leases, capex...)
A2: Example: Y | Owner draw - Partner A | Owner draws | Partner A | 50000 | Per month | 1 | 12
K3: 1 | L3: 2 | M3: 3 | N3: 4 | O3: 5 | P3: 6 | Q3: 7 | R3: 8 | S3: 9 | T3: 10 | U3: 11 | V3: 12
A4: Include (Y/N) | B4: Driver | C4: Section | D4: Person | E4: Amount ($) | F4: Basis | G4: Start month | H4: End month | I4: Annual total ($) | J4: Note | K4: Jan | L4: Feb | M4: Mar | N4: Apr | O4: May | P4: Jun | Q4: Jul | R4: Aug | S4: Sep | T4: Oct | U4: Nov | V4: Dec
A5: Y | B5: Owner draw - Partner A | C5: Owner draws | D5: Pat Owner | E5: 100000 | F5: Per month | G5: 1 | H5: 12 | I5: =SUM(K5:V5) -> 1200000 | K5: =IF($A5="Y",IF($F5="One-time",IF(K$3=$G5,$E5,0),IF(AND(K$3>=$G5,K$3<=MAX($H5,$G5)),IF($F5="Per year",$E5/(MAX($H5,$G5)-$G5+1),$E5),0)),0) -> 100000 | L5: =IF($A5="Y",IF($F5="One-time",IF(L$3=$G5,$E5,0),IF(AND(L$3>=$G5,L$3<=MAX($H5,$G5)),IF($F5="Per year",$E5/(MAX($H5,$G5)-$G5+1),$E5),0)),0) -> 100000 | M5: =IF($A5="Y",IF($F5="One-time",IF(M$3=$G5,$E5,0),IF(AND(M$3>=$G5,M$3<=MAX($H5,$G5)),IF($F5="Per year",$E5/(MAX($H5,$G5)-$G5+1),$E5),0)),0) -> 100000 | N5: =IF($A5="Y",IF($F5="One-time",IF(N$3=$G5,$E5,0),IF(AND(N$3>=$G5,N$3<=MAX($H5,$G5)),IF($F5="Per year",$E5/(MAX($H5,$G5)-$G5+1),$E5),0)),0) -> 100000 | O5: =IF($A5="Y",IF($F5="One-time",IF(O$3=$G5,$E5,0),IF(AND(O$3>=$G5,O$3<=MAX($H5,$G5)),IF($F5="Per year",$E5/(MAX($H5,$G5)-$G5+1),$E5),0)),0) -> 100000 | P5: =IF($A5="Y",IF($F5="One-time",IF(P$3=$G5,$E5,0),IF(AND(P$3>=$G5,P$3<=MAX($H5,$G5)),IF($F5="Per year",$E5/(MAX($H5,$G5)-$G5+1),$E5),0)),0) -> 100000 | Q5: =IF($A5="Y",IF($F5="One-time",IF(Q$3=$G5,$E5,0),IF(AND(Q$3>=$G5,Q$3<=MAX($H5,$G5)),IF($F5="Per year",$E5/(MAX($H5,$G5)-$G5+1),$E5),0)),0) -> 100000 | R5: =IF($A5="Y",IF($F5="One-time",IF(R$3=$G5,$E5,0),IF(AND(R$3>=$G5,R$3<=MAX($H5,$G5)),IF($F5="Per year",$E5/(MAX($H5,$G5)-$G5+1),$E5),0)),0) -> 100000 | ... V5: =IF($A5="Y",IF($F5="One-time",IF(V$3=$G5,$E5,0),IF(AND(V$3>=$G5,V$3<=MAX($H5,$G5)),IF($F5="Per year",$E5/(MAX($H5,$G5)-$G5+1),$E5),0)),0) -> 100000
A6: Y | B6: Owner draw - Partner B | C6: Owner draws | D6: Kim | E6: 30000 | F6: Per month | G6: 1 | H6: 12 | I6: =SUM(K6:V6) -> 360000 | K6: =IF($A6="Y",IF($F6="One-time",IF(K$3=$G6,$E6,0),IF(AND(K$3>=$G6,K$3<=MAX($H6,$G6)),IF($F6="Per year",$E6/(MAX($H6,$G6)-$G6+1),$E6),0)),0) -> 30000 | L6: =IF($A6="Y",IF($F6="One-time",IF(L$3=$G6,$E6,0),IF(AND(L$3>=$G6,L$3<=MAX($H6,$G6)),IF($F6="Per year",$E6/(MAX($H6,$G6)-$G6+1),$E6),0)),0) -> 30000 | M6: =IF($A6="Y",IF($F6="One-time",IF(M$3=$G6,$E6,0),IF(AND(M$3>=$G6,M$3<=MAX($H6,$G6)),IF($F6="Per year",$E6/(MAX($H6,$G6)-$G6+1),$E6),0)),0) -> 30000 | N6: =IF($A6="Y",IF($F6="One-time",IF(N$3=$G6,$E6,0),IF(AND(N$3>=$G6,N$3<=MAX($H6,$G6)),IF($F6="Per year",$E6/(MAX($H6,$G6)-$G6+1),$E6),0)),0) -> 30000 | O6: =IF($A6="Y",IF($F6="One-time",IF(O$3=$G6,$E6,0),IF(AND(O$3>=$G6,O$3<=MAX($H6,$G6)),IF($F6="Per year",$E6/(MAX($H6,$G6)-$G6+1),$E6),0)),0) -> 30000 | P6: =IF($A6="Y",IF($F6="One-time",IF(P$3=$G6,$E6,0),IF(AND(P$3>=$G6,P$3<=MAX($H6,$G6)),IF($F6="Per year",$E6/(MAX($H6,$G6)-$G6+1),$E6),0)),0) -> 30000 | Q6: =IF($A6="Y",IF($F6="One-time",IF(Q$3=$G6,$E6,0),IF(AND(Q$3>=$G6,Q$3<=MAX($H6,$G6)),IF($F6="Per year",$E6/(MAX($H6,$G6)-$G6+1),$E6),0)),0) -> 30000 | R6: =IF($A6="Y",IF($F6="One-time",IF(R$3=$G6,$E6,0),IF(AND(R$3>=$G6,R$3<=MAX($H6,$G6)),IF($F6="Per year",$E6/(MAX($H6,$G6)-$G6+1),$E6),0)),0) -> 30000 | ... V6: =IF($A6="Y",IF($F6="One-time",IF(V$3=$G6,$E6,0),IF(AND(V$3>=$G6,V$3<=MAX($H6,$G6)),IF($F6="Per year",$E6/(MAX($H6,$G6)-$G6+1),$E6),0)),0) -> 30000
A7: Y | B7: Year-end bonus pool | C7: Personnel | E7: 120000 | F7: One-time | G7: 12 | H7: 12 | I7: =SUM(K7:V7) -> 120000 | K7: =IF($A7="Y",IF($F7="One-time",IF(K$3=$G7,$E7,0),IF(AND(K$3>=$G7,K$3<=MAX($H7,$G7)),IF($F7="Per year",$E7/(MAX($H7,$G7)-$G7+1),$E7),0)),0) -> 0 | L7: =IF($A7="Y",IF($F7="One-time",IF(L$3=$G7,$E7,0),IF(AND(L$3>=$G7,L$3<=MAX($H7,$G7)),IF($F7="Per year",$E7/(MAX($H7,$G7)-$G7+1),$E7),0)),0) -> 0 | M7: =IF($A7="Y",IF($F7="One-time",IF(M$3=$G7,$E7,0),IF(AND(M$3>=$G7,M$3<=MAX($H7,$G7)),IF($F7="Per year",$E7/(MAX($H7,$G7)-$G7+1),$E7),0)),0) -> 0 | N7: =IF($A7="Y",IF($F7="One-time",IF(N$3=$G7,$E7,0),IF(AND(N$3>=$G7,N$3<=MAX($H7,$G7)),IF($F7="Per year",$E7/(MAX($H7,$G7)-$G7+1),$E7),0)),0) -> 0 | O7: =IF($A7="Y",IF($F7="One-time",IF(O$3=$G7,$E7,0),IF(AND(O$3>=$G7,O$3<=MAX($H7,$G7)),IF($F7="Per year",$E7/(MAX($H7,$G7)-$G7+1),$E7),0)),0) -> 0 | P7: =IF($A7="Y",IF($F7="One-time",IF(P$3=$G7,$E7,0),IF(AND(P$3>=$G7,P$3<=MAX($H7,$G7)),IF($F7="Per year",$E7/(MAX($H7,$G7)-$G7+1),$E7),0)),0) -> 0 | Q7: =IF($A7="Y",IF($F7="One-time",IF(Q$3=$G7,$E7,0),IF(AND(Q$3>=$G7,Q$3<=MAX($H7,$G7)),IF($F7="Per year",$E7/(MAX($H7,$G7)-$G7+1),$E7),0)),0) -> 0 | R7: =IF($A7="Y",IF($F7="One-time",IF(R$3=$G7,$E7,0),IF(AND(R$3>=$G7,R$3<=MAX($H7,$G7)),IF($F7="Per year",$E7/(MAX($H7,$G7)-$G7+1),$E7),0)),0) -> 0 | ... V7: =IF($A7="Y",IF($F7="One-time",IF(V$3=$G7,$E7,0),IF(AND(V$3>=$G7,V$3<=MAX($H7,$G7)),IF($F7="Per year",$E7/(MAX($H7,$G7)-$G7+1),$E7),0)),0) -> 120000
A8: Y | B8: New office lease | C8: Operating expense | E8: 60000 | F8: Per year | G8: 7 | H8: 12 | I8: =SUM(K8:V8) -> 60000 | K8: =IF($A8="Y",IF($F8="One-time",IF(K$3=$G8,$E8,0),IF(AND(K$3>=$G8,K$3<=MAX($H8,$G8)),IF($F8="Per year",$E8/(MAX($H8,$G8)-$G8+1),$E8),0)),0) -> 0 | L8: =IF($A8="Y",IF($F8="One-time",IF(L$3=$G8,$E8,0),IF(AND(L$3>=$G8,L$3<=MAX($H8,$G8)),IF($F8="Per year",$E8/(MAX($H8,$G8)-$G8+1),$E8),0)),0) -> 0 | M8: =IF($A8="Y",IF($F8="One-time",IF(M$3=$G8,$E8,0),IF(AND(M$3>=$G8,M$3<=MAX($H8,$G8)),IF($F8="Per year",$E8/(MAX($H8,$G8)-$G8+1),$E8),0)),0) -> 0 | N8: =IF($A8="Y",IF($F8="One-time",IF(N$3=$G8,$E8,0),IF(AND(N$3>=$G8,N$3<=MAX($H8,$G8)),IF($F8="Per year",$E8/(MAX($H8,$G8)-$G8+1),$E8),0)),0) -> 0 | O8: =IF($A8="Y",IF($F8="One-time",IF(O$3=$G8,$E8,0),IF(AND(O$3>=$G8,O$3<=MAX($H8,$G8)),IF($F8="Per year",$E8/(MAX($H8,$G8)-$G8+1),$E8),0)),0) -> 0 | P8: =IF($A8="Y",IF($F8="One-time",IF(P$3=$G8,$E8,0),IF(AND(P$3>=$G8,P$3<=MAX($H8,$G8)),IF($F8="Per year",$E8/(MAX($H8,$G8)-$G8+1),$E8),0)),0) -> 0 | Q8: =IF($A8="Y",IF($F8="One-time",IF(Q$3=$G8,$E8,0),IF(AND(Q$3>=$G8,Q$3<=MAX($H8,$G8)),IF($F8="Per year",$E8/(MAX($H8,$G8)-$G8+1),$E8),0)),0) -> 10000 | R8: =IF($A8="Y",IF($F8="One-time",IF(R$3=$G8,$E8,0),IF(AND(R$3>=$G8,R$3<=MAX($H8,$G8)),IF($F8="Per year",$E8/(MAX($H8,$G8)-$G8+1),$E8),0)),0) -> 10000 | ... V8: =IF($A8="Y",IF($F8="One-time",IF(V$3=$G8,$E8,0),IF(AND(V$3>=$G8,V$3<=MAX($H8,$G8)),IF($F8="Per year",$E8/(MAX($H8,$G8)-$G8+1),$E8),0)),0) -> 10000
I9: =SUM(K9:V9) -> 0 | K9: =IF($A9="Y",IF($F9="One-time",IF(K$3=$G9,$E9,0),IF(AND(K$3>=$G9,K$3<=MAX($H9,$G9)),IF($F9="Per year",$E9/(MAX($H9,$G9)-$G9+1),$E9),0)),0) -> 0 | L9: =IF($A9="Y",IF($F9="One-time",IF(L$3=$G9,$E9,0),IF(AND(L$3>=$G9,L$3<=MAX($H9,$G9)),IF($F9="Per year",$E9/(MAX($H9,$G9)-$G9+1),$E9),0)),0) -> 0 | M9: =IF($A9="Y",IF($F9="One-time",IF(M$3=$G9,$E9,0),IF(AND(M$3>=$G9,M$3<=MAX($H9,$G9)),IF($F9="Per year",$E9/(MAX($H9,$G9)-$G9+1),$E9),0)),0) -> 0 | N9: =IF($A9="Y",IF($F9="One-time",IF(N$3=$G9,$E9,0),IF(AND(N$3>=$G9,N$3<=MAX($H9,$G9)),IF($F9="Per year",$E9/(MAX($H9,$G9)-$G9+1),$E9),0)),0) -> 0 | O9: =IF($A9="Y",IF($F9="One-time",IF(O$3=$G9,$E9,0),IF(AND(O$3>=$G9,O$3<=MAX($H9,$G9)),IF($F9="Per year",$E9/(MAX($H9,$G9)-$G9+1),$E9),0)),0) -> 0 | P9: =IF($A9="Y",IF($F9="One-time",IF(P$3=$G9,$E9,0),IF(AND(P$3>=$G9,P$3<=MAX($H9,$G9)),IF($F9="Per year",$E9/(MAX($H9,$G9)-$G9+1),$E9),0)),0) -> 0 | Q9: =IF($A9="Y",IF($F9="One-time",IF(Q$3=$G9,$E9,0),IF(AND(Q$3>=$G9,Q$3<=MAX($H9,$G9)),IF($F9="Per year",$E9/(MAX($H9,$G9)-$G9+1),$E9),0)),0) -> 0 | R9: =IF($A9="Y",IF($F9="One-time",IF(R$3=$G9,$E9,0),IF(AND(R$3>=$G9,R$3<=MAX($H9,$G9)),IF($F9="Per year",$E9/(MAX($H9,$G9)-$G9+1),$E9),0)),0) -> 0 | ... V9: =IF($A9="Y",IF($F9="One-time",IF(V$3=$G9,$E9,0),IF(AND(V$3>=$G9,V$3<=MAX($H9,$G9)),IF($F9="Per year",$E9/(MAX($H9,$G9)-$G9+1),$E9),0)),0) -> 0
